{
  "last_updated":1680726940,
  "projects": [
    {
        "title":"devrant-lite",
        "os":"",
        "type":"",
        "timestamp_added":1680726940,
        "desc": "",
        "relevant_dr_url":"A tiny, fully-featured REST client for the unofficial devRant API",
        "website": "",
        "github": "https://github.com/Skayo/devrant-lite",
        "language": "",
        "active": false
      },{
        "title":"devrant-bot",
        "os":"",
        "type":"library",
        "timestamp_added":1680726940,
        "desc": "",
        "relevant_dr_url":"A wrapper for DevRant API specifically to create bots",
        "website": "",
        "github": "https://github.com/theabbie/devrant-bot",
        "language": "",
        "active": false
      },{
        "title":"ts-devrant",
        "os":"",
        "type":"library",
        "timestamp_added":1680726940,
        "desc": "Isomorphic, TypeScript based wrapper for the devRant API (inspired by RantScript)",
        "relevant_dr_url":"",
        "website": "",
        "github": "https://github.com/dr010001111/ts-devrant/",
        "language": "TypeScript",
        "active": false
      },{
        "title":"devRant-JS",
        "os":"",
        "type":"library",
        "timestamp_added":1680726940,
        "desc": "A JavaScript wrapper for the devRant API",
        "relevant_dr_url":"",
        "website": "",
        "github": "https://github.com/danillouz/devrant",
        "language": "JavaScript",
        "active": false
      },{
        "title":"devRant-API",
        "os":"",
        "type":"library",
        "timestamp_added":1680726940,
        "desc": "A JavaScript wrapper for the devRant API",
        "relevant_dr_url":"",
        "website": "",
        "github": "https://github.com/nblackburn/devrant-api",
        "language": "JavaScript",
        "active": false
      },{
        "title":"/dev/rant",
        "os":"Linux",
        "type":"client",
        "timestamp_added":1680726940,
        "desc": "A simple devrant.com integration into Linux via /dev/rant",
        "relevant_dr_url":"",
        "website": "https://gitlab.com/netikras/dev_rant_linux",
        "github": "",
        "language": "bash",
        "active": false
      },{
        "title":"devRant CLI",
        "os":"",
        "type":"client",
        "timestamp_added":1680726940,
        "desc": "devRant terminal client with ASCII image conversion",
        "relevant_dr_url":"",
        "website": "",
        "github": "https://github.com/kurtr/devRantCLI",
        "language": "JavaScript",
        "active": false
      },{
        "title":"devRant-computercraft",
        "os":"",
        "type":"client",
        "timestamp_added":1680726940,
        "desc": "devRant client written in Lua for ComputerCraft computers. (Minecraft Stuff)",
        "relevant_dr_url":"",
        "website": "",
        "github": "https://github.com/olback/devRant-computercraft",
        "language": "Lua",
        "active": false
      },{
        "title":"Terminal devRant",
        "os":"",
        "type":"client",
        "timestamp_added":1680726940,
        "desc": "A devRant viewer in the terminal",
        "relevant_dr_url":"",
        "website": "",
        "github": "https://github.com/Invisible-Rabbit-Hunter/terminal_devrant",
        "language": "C++",
        "active": false
      },{
        "title":"dr",
        "os":"Linux, OSX, ChromeOS",
        "type":"client",
        "timestamp_added":1680726940,
        "desc": "An ed-like devrant client with support for chromebooks",
        "relevant_dr_url":"",
        "website": "",
        "github": "https://github.com/ewpratten/dr",
        "language": "python",
        "active": false
      },{
        "title":"devRant Chrome Extension",
        "os":"Chrome",
        "type":"client",
        "timestamp_added":1680726940,
        "desc": "A devRant client for Chrome for quickly browsing the feed without leaving the site",
        "relevant_dr_url":"",
        "website": "https://chrome.google.com/webstore/detail/un-official-devrant-chrom/nhilbnepbfofblijmiiihfkdgmnnblie",
        "github": "",
        "language": "",
        "active": true
      },{
        "title":"jsRant",
        "os":"Windows",
        "type":"client",
        "timestamp_added":1680726940,
        "desc": "Navigate the devRant feed in JSON format. Perfect for browsing devRant at work!",
        "relevant_dr_url":"",
        "website": "http://www.jsrant.com/",
        "github": "",
        "language": "JavaScript",
        "active": true
      },{
        "title":"devRant UWP",
        "os":"Windows",
        "type":"client",
        "timestamp_added":1680726940,
        "desc": "The first and unique 'devRant' (unofficial) client for Windows 10!",
        "relevant_dr_url":"",
        "website": "https://apps.microsoft.com/store/detail/devrant-uwp/9NBLGGH43LXR?hl=en-us&gl=us&rtc=1",
        "github": "https://github.com/JakubSteplowski/devRantUWP",
        "language": "JavaScript",
        "active": false
      },{
        "title":"devRanton",
        "os":"Windows, Linux, macOS",
        "type":"client",
        "timestamp_added":1680726940,
        "desc": "An open source devRant client.\nBuilt for the community by the community.",
        "relevant_dr_url":"",
        "website": "https://devrantron.firebaseapp.com/",
        "github": "https://github.com/tahnik/devRantron",
        "language": "JavaScript",
        "active": false
      },{
        "title":"Awesome devRant",
        "os":"any",
        "type":"documentation",
        "timestamp_added":1680726940,
        "desc": "A curated list of awesome devRant projects, libraries, software and resources",
        "relevant_dr_url":"",
        "website": "",
        "github": "https://github.com/devRant-Community/awesome-devrant",
        "language": "md",
        "active": true
      },{
        "title":"altRant",
        "os":"iOS",
        "type":"client",
        "timestamp_added":1680726940,
        "desc": "Unofficial devRant iOS app made with Swift + UIKit Framework.",
        "relevant_dr_url":"",
        "website": "",
        "github": "https://github.com/OmerFlame/AltRant",
        "language": "Swift",
        "active": true
      },{
        "title":"joyRant",
        "os":"iOS & macOS",
        "type":"client",
        "timestamp_added":1680726940,
        "desc": "An unofficial devRant client for iOS and macOS, that doesn't crash.",
        "relevant_dr_url":"",
        "website": "https://testflight.apple.com/join/NoiaKmoN",
        "github": "https://github.com/WilhelmOks/JoyRant",
        "language": "Swift",
        "active": true
      },{
        "title":"watchRant",
        "os":"wear-os",
        "type":"client",
        "timestamp_added":1680726940,
        "desc": "A devRant client for your watch!",
        "relevant_dr_url":"",
        "website": "https://play.google.com/store/apps/details?id=com.dev.watchrant",
        "github": "https://github.com/joewilliams007/watchRant",
        "language": "Java",
        "active": true
      },{
        "title":"skyRant",
        "os":"android",
        "type":"client",
        "timestamp_added":1680726940,
        "desc": "devRant client for Android with a focus on Animations",
        "relevant_dr_url":"",
        "website": "",
        "github": "https://github.com/joewilliams007/skyRant",
        "language": "Java",
        "active": true
      },{
        "title":"Discord Server",
        "os":"any",
        "type":"other",
        "timestamp_added":1680726940,
        "desc": "discord server",
        "relevant_dr_url":"https://devrant.com/collabs/3221539",
        "website": "https://discord.gg/jMp64VH",
        "github": "",
        "language": "",
        "active": true
      }
  ]
}
